README.rst
setup.py
AITAToolbox/__init__.py
AITAToolbox/aita.py
AITAToolbox/image2d.py
AITAToolbox/loadData_aita.py
AITAToolbox/setvector3d.py
AITAToolbox/uniform_dist.py
AITAToolbox.egg-info/PKG-INFO
AITAToolbox.egg-info/SOURCES.txt
AITAToolbox.egg-info/dependency_links.txt
AITAToolbox.egg-info/requires.txt
AITAToolbox.egg-info/top_level.txt