Metadata-Version: 1.2
Name: AITAToolbox
Version: 2.2.1
Summary: Tools for AITA.
Home-page: https://github.com/ThomasChauve/aita
Author: Thomas Chauve
Author-email: thomas.chauve@univ-grenoble-alpes.fr
License: GPL-3.0
Platform: UNKNOWN
Classifier: Intended Audience :: Science/Research
Classifier: License :: OSI Approved :: GNU General Public License v3 (GPLv3)
Classifier: Operating System :: OS Independent
Classifier: Programming Language :: Python :: 3 :: Only
Requires-Python: >=3.8
